{"metrics":[{"id":"jsm-total-number-of-breached--1","name":"JSM Total Number of Breached SLAs","description":"Total number of breached SLAs","signalFragment":"sum(\"SLA Count Breaches\")","variables":[],"aggregationType":"CASE","createdAt":"2023-05-17T12:21:51.005767Z"},{"id":"jsm-average-resolution-time-1","name":"JSM Average Resolution Time","description":"Average time from issue creation to its resolution","signalFragment":"AVG(\"Issue Resolution Date\" - \"Issue Created Date\" ) FILTER (WHERE \"Resolution\" IS NOT NULL)\n","variables":[],"aggregationType":"CASE","createdAt":"2023-05-17T12:21:51.005767Z"},{"id":"jsm-average-response-time-1","name":"JSM Average Response Time","description":"Average time from issue creation to its response","signalFragment":"AVG(\"First Response Date\" - \"Issue Created Date\")\n","variables":[],"aggregationType":"CASE","createdAt":"2023-05-17T12:21:51.005767Z"},{"id":"jsm-total-number-of-open-issu-1","name":"JSM Total Number of Open Issues","description":"Total number of open issues","signalFragment":"count(\"case_id\") FILTER ( WHERE \"Current Status category\" != 'Done')","variables":[],"aggregationType":"CASE","createdAt":"2023-05-17T12:21:51.005767Z"}],"metricsVariables":[],"processVariables":[{"id":"actual-end-date-1","name":"Actual End Date","displayName":"Actual End Date","dataType":"TIMESTAMP_WITH_TIME_ZONE","level":"CASE"},{"id":"actual-start-date-3","name":"Actual Start Date","displayName":"Actual Start Date","dataType":"TIMESTAMP_WITH_TIME_ZONE","level":"CASE"},{"id":"affected-hardware-1","name":"Affected Hardware","displayName":"Affected Hardware","dataType":"CHOICE","level":"CASE"},{"id":"change-reason-1","name":"Change Reason","displayName":"Change Reason","dataType":"CHOICE","level":"CASE"},{"id":"change-risk-1","name":"Change Risk","displayName":"Change Risk","dataType":"CHOICE","level":"CASE"},{"id":"change-type-70","name":"Change Type","displayName":"Change Type","dataType":"CHOICE","level":"CASE"},{"id":"creator-1","name":"Creator","displayName":"Creator","dataType":"CHOICE","level":"CASE"},{"id":"current-assignee-1","name":"Current Assignee","displayName":"Current Assignee","dataType":"CHOICE","level":"CASE"},{"id":"current-impact-1","name":"Current Impact","displayName":"Current Impact","dataType":"CHOICE","level":"CASE"},{"id":"current-priority-1","name":"Current Priority","displayName":"Current Priority","dataType":"CHOICE","level":"CASE"},{"id":"current-reporter-1","name":"Current Reporter","displayName":"Current Reporter","dataType":"CHOICE","level":"CASE"},{"id":"current-severity-1","name":"Current Severity","displayName":"Current Severity","dataType":"CHOICE","level":"CASE"},{"id":"current-status-2","name":"Current Status","displayName":"Current Status","dataType":"CHOICE","level":"CASE"},{"id":"current-status-category-1","name":"Current Status Category","displayName":"Current Status Category","dataType":"CHOICE","level":"CASE"},{"id":"current-team-1","name":"Current Team","displayName":"Current Team","dataType":"CHOICE","level":"CASE"},{"id":"current-urgency-1","name":"Current Urgency","displayName":"Current Urgency","dataType":"CHOICE","level":"CASE"},{"id":"customer-comment-count-1","name":"Customer Comment Count","displayName":"Customer Comment Count","dataType":"DOUBLE_PRECISION","level":"CASE"},{"id":"employee-comment-count-1","name":"Employee Comment Count","displayName":"Employee Comment Count","dataType":"DOUBLE_PRECISION","level":"CASE"},{"id":"environment-1","name":"Environment","displayName":"Environment","dataType":"CHOICE","level":"CASE"},{"id":"extraction-date-1","name":"Extraction Date","displayName":"Extraction Date","dataType":"TIMESTAMP_WITH_TIME_ZONE","level":"CASE"},{"id":"first-employee-comment-date-1","name":"First Employee Comment Date","displayName":"First Employee Comment Date","dataType":"TIMESTAMP_WITH_TIME_ZONE","level":"CASE"},{"id":"first-response-date-1","name":"First Response Date","displayName":"First Response Date","dataType":"TIMESTAMP_WITH_TIME_ZONE","level":"CASE"},{"id":"first-waiting-for-customer-da-1","name":"First Waiting for Customer Date","displayName":"First Waiting for Customer Date","dataType":"TIMESTAMP_WITH_TIME_ZONE","level":"CASE"},{"id":"investigation-reason-1","name":"Investigation Reason","displayName":"Investigation Reason","dataType":"CHOICE","level":"CASE"},{"id":"inward-issue-links-count-1","name":"Inward Issue Links Count","displayName":"Inward Issue Links Count","dataType":"DOUBLE_PRECISION","level":"CASE"},{"id":"issue-created-date-1","name":"Issue Created Date","displayName":"Issue Created Date","dataType":"TIMESTAMP_WITH_TIME_ZONE","level":"CASE"},{"id":"issue-due-date-1","name":"Issue Due Date","displayName":"Issue Due Date","dataType":"TIMESTAMP_WITH_TIME_ZONE","level":"CASE"},{"id":"issue-key-1","name":"Issue Key","displayName":"Issue Key","dataType":"CHOICE","level":"CASE"},{"id":"issue-last-viewed-date-1","name":"Issue Last Viewed Date","displayName":"Issue Last Viewed Date","dataType":"TIMESTAMP_WITH_TIME_ZONE","level":"CASE"},{"id":"issue-resolution-date-1","name":"Issue Resolution Date","displayName":"Issue Resolution Date","dataType":"TIMESTAMP_WITH_TIME_ZONE","level":"CASE"},{"id":"issue-type-1","name":"Issue Type","displayName":"Issue Type","dataType":"CHOICE","level":"CASE"},{"id":"issue-updated-date-1","name":"Issue Updated Date","displayName":"Issue Updated Date","dataType":"TIMESTAMP_WITH_TIME_ZONE","level":"CASE"},{"id":"labels-1","name":"Labels","displayName":"Labels","dataType":"CHOICE","level":"CASE"},{"id":"major-incident-1","name":"Major Incident","displayName":"Major Incident","dataType":"CHOICE","level":"CASE"},{"id":"operational-categorization-1","name":"Operational Categorization","displayName":"Operational Categorization","dataType":"CHOICE","level":"CASE"},{"id":"originial-estimate-seconds-1","name":"Originial Estimate (seconds)","displayName":"Originial Estimate (seconds)","dataType":"DOUBLE_PRECISION","level":"CASE"},{"id":"outward-issue-links-count-1","name":"Outward Issue Links Count","displayName":"Outward Issue Links Count","dataType":"DOUBLE_PRECISION","level":"CASE"},{"id":"pending-reason-1","name":"Pending Reason","displayName":"Pending Reason","dataType":"CHOICE","level":"CASE"},{"id":"planned-end-date-1","name":"Planned End Date","displayName":"Planned End Date","dataType":"TIMESTAMP_WITH_TIME_ZONE","level":"CASE"},{"id":"planned-start-date-1","name":"Planned Start Date","displayName":"Planned Start Date","dataType":"TIMESTAMP_WITH_TIME_ZONE","level":"CASE"},{"id":"product-categorization-1","name":"Product Categorization","displayName":"Product Categorization","dataType":"CHOICE","level":"CASE"},{"id":"project-1","name":"Project","displayName":"Project","dataType":"CHOICE","level":"CASE"},{"id":"remaining-estimate-seconds-1","name":"Remaining Estimate (seconds)","displayName":"Remaining Estimate (seconds)","dataType":"DOUBLE_PRECISION","level":"CASE"},{"id":"request-language-1","name":"Request Language","displayName":"Request Language","dataType":"CHOICE","level":"CASE"},{"id":"request-type-11","name":"Request Type","displayName":"Request Type","dataType":"CHOICE","level":"CASE"},{"id":"resolution-3","name":"Resolution","displayName":"Resolution","dataType":"CHOICE","level":"CASE"},{"id":"satisfaction-1","name":"Satisfaction","displayName":"Satisfaction","dataType":"DOUBLE_PRECISION","level":"CASE"},{"id":"satisfaction-date-1","name":"Satisfaction Date","displayName":"Satisfaction Date","dataType":"TIMESTAMP_WITH_TIME_ZONE","level":"CASE"},{"id":"sla-count-breaches-1","name":"SLA Count Breaches","displayName":"SLA Count Breaches","dataType":"DOUBLE_PRECISION","level":"CASE"},{"id":"sla-count-completed-1","name":"SLA Count Completed","displayName":"SLA Count Completed","dataType":"DOUBLE_PRECISION","level":"CASE"},{"id":"sla-count-ongoing-1","name":"SLA Count Ongoing","displayName":"SLA Count Ongoing","dataType":"DOUBLE_PRECISION","level":"CASE"},{"id":"sla-count-paused-1","name":"SLA Count Paused","displayName":"SLA Count Paused","dataType":"DOUBLE_PRECISION","level":"CASE"},{"id":"sla-definition-count-1","name":"SLA Definition Count","displayName":"SLA Definition Count","dataType":"DOUBLE_PRECISION","level":"CASE"},{"id":"summary-36","name":"Summary","displayName":"Summary","dataType":"CHOICE","level":"CASE"},{"id":"target-end-date-1","name":"Target End Date","displayName":"Target End Date","dataType":"TIMESTAMP_WITH_TIME_ZONE","level":"CASE"},{"id":"target-start-date-1","name":"Target Start Date","displayName":"Target Start Date","dataType":"TIMESTAMP_WITH_TIME_ZONE","level":"CASE"},{"id":"url-1","name":"URL","displayName":"URL","dataType":"CHOICE","level":"CASE"},{"id":"work-category-1","name":"Work Category","displayName":"Work Category","dataType":"CHOICE","level":"CASE"}],"investigation":{"name":"Issue-to-Resolution","rootWidget":{"name":"root chapter","id":"root-chapter-332","visualization":{"type":"CHAPTER"},"filters":[],"children":[{"name":"Process Discovery","id":"process-discovery-524","visualization":{"type":"FUZZY_MODEL","edgeGranularity":0,"nodeGranularity":2,"width":"HALF"},"dataSource":{"type":"STRUCTURED","projections":[{"type":"PARAMETERIZED","attribute":"OCCURRENCES","aggregation":"SUM","parameter":{"type":"SEMANTIC_TYPE","semanticType":"OCCURRENCES"}}]},"filters":[{"type":"CASE_ID","id":"caseid-125","enabled":true,"includes":["10022.0"]}],"children":[]},{"name":"Total Number of Open Issues","id":"total-number-of-open-issues-1","visualization":{"type":"VALUE"},"dataSource":{"type":"STRUCTURED","projections":[{"type":"METRIC","metric":"jsm-total-number-of-open-issu-1"}]},"filters":[],"children":[]},{"name":"Total Number of Breached SLAs","id":"total-number-of-breached-slas-1","visualization":{"type":"VALUE"},"dataSource":{"type":"STRUCTURED","projections":[{"type":"METRIC","metric":"jsm-total-number-of-breached--1"}]},"filters":[],"children":[]},{"name":"Average Response Time","id":"average-response-time-1","visualization":{"type":"VALUE"},"dataSource":{"type":"STRUCTURED","projections":[{"type":"METRIC","metric":"jsm-average-response-time-1"}]},"filters":[],"children":[]},{"name":"Average Resolution Time","id":"average-resolution-time-1","visualization":{"type":"VALUE"},"dataSource":{"type":"STRUCTURED","projections":[{"type":"METRIC","metric":"jsm-average-resolution-time-1"}]},"filters":[],"children":[]},{"name":"Value","id":"value-163","visualization":{"type":"VALUE"},"dataSource":{"type":"SIGNAL","query":"SELECT\nCOUNT(case_id) FILTER (\n\tWHERE (SELECT FIRST(event_name) \n\t\t\tWHERE event_name LIKE '') IS NOT NULL) \n/\nCOUNT ( DISTINCT (case_id))\n*100\nFROM THIS_PROCESS"},"filters":[],"children":[]},{"name":"A","id":"a-2","visualization":{"type":"CHAPTER"},"filters":[],"children":[{"name":"Case Table","id":"case-table-174","visualization":{"type":"CASES_TABLE","columnConfigurations":[]},"dataSource":{"type":"STRUCTURED","projections":[{"type":"PARAMETERIZED","attribute":"CASE_ID","parameter":{"type":"SEMANTIC_TYPE","semanticType":"CASE_ID"}},{"type":"PARAMETERIZED","attribute":"EVENT_COUNT","parameter":{"type":"SEMANTIC_TYPE","semanticType":"EVENT_COUNT"}},{"type":"PARAMETERIZED","attribute":"CYCLE_TIME","parameter":{"type":"SEMANTIC_TYPE","semanticType":"CYCLE_TIME"}},{"type":"PARAMETERIZED","attribute":"CASE_START","parameter":{"type":"SEMANTIC_TYPE","semanticType":"CASE_START"}},{"type":"PARAMETERIZED","attribute":"CASE_END","parameter":{"type":"SEMANTIC_TYPE","semanticType":"CASE_END"}},{"type":"PARAMETERIZED","attribute":"actual-end-date-1","parameter":{"type":"PROCESS_VARIABLE","name":"Actual End Date"}},{"type":"PARAMETERIZED","attribute":"actual-start-date-3","parameter":{"type":"PROCESS_VARIABLE","name":"Actual Start Date"}},{"type":"PARAMETERIZED","attribute":"affected-hardware-1","parameter":{"type":"PROCESS_VARIABLE","name":"Affected Hardware"}},{"type":"PARAMETERIZED","attribute":"change-reason-1","parameter":{"type":"PROCESS_VARIABLE","name":"Change Reason"}},{"type":"PARAMETERIZED","attribute":"change-risk-1","parameter":{"type":"PROCESS_VARIABLE","name":"Change Risk"}},{"type":"PARAMETERIZED","attribute":"change-type-70","parameter":{"type":"PROCESS_VARIABLE","name":"Change Type"}},{"type":"PARAMETERIZED","attribute":"creator-1","parameter":{"type":"PROCESS_VARIABLE","name":"Creator"}},{"type":"PARAMETERIZED","attribute":"current-assignee-1","parameter":{"type":"PROCESS_VARIABLE","name":"Current Assignee"}},{"type":"PARAMETERIZED","attribute":"current-impact-1","parameter":{"type":"PROCESS_VARIABLE","name":"Current Impact"}},{"type":"PARAMETERIZED","attribute":"current-priority-1","parameter":{"type":"PROCESS_VARIABLE","name":"Current Priority"}},{"type":"PARAMETERIZED","attribute":"current-reporter-1","parameter":{"type":"PROCESS_VARIABLE","name":"Current Reporter"}},{"type":"PARAMETERIZED","attribute":"current-severity-1","parameter":{"type":"PROCESS_VARIABLE","name":"Current Severity"}},{"type":"PARAMETERIZED","attribute":"current-status-2","parameter":{"type":"PROCESS_VARIABLE","name":"Current Status"}},{"type":"PARAMETERIZED","attribute":"current-status-category-1","parameter":{"type":"PROCESS_VARIABLE","name":"Current Status Category"}},{"type":"PARAMETERIZED","attribute":"current-team-1","parameter":{"type":"PROCESS_VARIABLE","name":"Current Team"}},{"type":"PARAMETERIZED","attribute":"current-urgency-1","parameter":{"type":"PROCESS_VARIABLE","name":"Current Urgency"}},{"type":"PARAMETERIZED","attribute":"customer-comment-count-1","parameter":{"type":"PROCESS_VARIABLE","name":"Customer Comment Count"}},{"type":"PARAMETERIZED","attribute":"employee-comment-count-1","parameter":{"type":"PROCESS_VARIABLE","name":"Employee Comment Count"}},{"type":"PARAMETERIZED","attribute":"environment-1","parameter":{"type":"PROCESS_VARIABLE","name":"Environment"}},{"type":"PARAMETERIZED","attribute":"extraction-date-1","parameter":{"type":"PROCESS_VARIABLE","name":"Extraction Date"}},{"type":"PARAMETERIZED","attribute":"first-employee-comment-date-1","parameter":{"type":"PROCESS_VARIABLE","name":"First Employee Comment Date"}},{"type":"PARAMETERIZED","attribute":"first-response-date-1","parameter":{"type":"PROCESS_VARIABLE","name":"First Response Date"}},{"type":"PARAMETERIZED","attribute":"first-waiting-for-customer-da-1","parameter":{"type":"PROCESS_VARIABLE","name":"First Waiting for Customer Date"}},{"type":"PARAMETERIZED","attribute":"investigation-reason-1","parameter":{"type":"PROCESS_VARIABLE","name":"Investigation Reason"}},{"type":"PARAMETERIZED","attribute":"inward-issue-links-count-1","parameter":{"type":"PROCESS_VARIABLE","name":"Inward Issue Links Count"}},{"type":"PARAMETERIZED","attribute":"issue-created-date-1","parameter":{"type":"PROCESS_VARIABLE","name":"Issue Created Date"}},{"type":"PARAMETERIZED","attribute":"issue-due-date-1","parameter":{"type":"PROCESS_VARIABLE","name":"Issue Due Date"}},{"type":"PARAMETERIZED","attribute":"issue-key-1","parameter":{"type":"PROCESS_VARIABLE","name":"Issue Key"}},{"type":"PARAMETERIZED","attribute":"issue-last-viewed-date-1","parameter":{"type":"PROCESS_VARIABLE","name":"Issue Last Viewed Date"}},{"type":"PARAMETERIZED","attribute":"issue-resolution-date-1","parameter":{"type":"PROCESS_VARIABLE","name":"Issue Resolution Date"}},{"type":"PARAMETERIZED","attribute":"issue-type-1","parameter":{"type":"PROCESS_VARIABLE","name":"Issue Type"}},{"type":"PARAMETERIZED","attribute":"issue-updated-date-1","parameter":{"type":"PROCESS_VARIABLE","name":"Issue Updated Date"}},{"type":"PARAMETERIZED","attribute":"labels-1","parameter":{"type":"PROCESS_VARIABLE","name":"Labels"}},{"type":"PARAMETERIZED","attribute":"major-incident-1","parameter":{"type":"PROCESS_VARIABLE","name":"Major Incident"}},{"type":"PARAMETERIZED","attribute":"operational-categorization-1","parameter":{"type":"PROCESS_VARIABLE","name":"Operational Categorization"}},{"type":"PARAMETERIZED","attribute":"originial-estimate-seconds-1","parameter":{"type":"PROCESS_VARIABLE","name":"Originial Estimate (seconds)"}},{"type":"PARAMETERIZED","attribute":"outward-issue-links-count-1","parameter":{"type":"PROCESS_VARIABLE","name":"Outward Issue Links Count"}},{"type":"PARAMETERIZED","attribute":"pending-reason-1","parameter":{"type":"PROCESS_VARIABLE","name":"Pending Reason"}},{"type":"PARAMETERIZED","attribute":"planned-end-date-1","parameter":{"type":"PROCESS_VARIABLE","name":"Planned End Date"}},{"type":"PARAMETERIZED","attribute":"planned-start-date-1","parameter":{"type":"PROCESS_VARIABLE","name":"Planned Start Date"}},{"type":"PARAMETERIZED","attribute":"product-categorization-1","parameter":{"type":"PROCESS_VARIABLE","name":"Product Categorization"}},{"type":"PARAMETERIZED","attribute":"project-1","parameter":{"type":"PROCESS_VARIABLE","name":"Project"}},{"type":"PARAMETERIZED","attribute":"remaining-estimate-seconds-1","parameter":{"type":"PROCESS_VARIABLE","name":"Remaining Estimate (seconds)"}},{"type":"PARAMETERIZED","attribute":"request-language-1","parameter":{"type":"PROCESS_VARIABLE","name":"Request Language"}},{"type":"PARAMETERIZED","attribute":"request-type-11","parameter":{"type":"PROCESS_VARIABLE","name":"Request Type"}},{"type":"PARAMETERIZED","attribute":"resolution-3","parameter":{"type":"PROCESS_VARIABLE","name":"Resolution"}},{"type":"PARAMETERIZED","attribute":"satisfaction-1","parameter":{"type":"PROCESS_VARIABLE","name":"Satisfaction"}},{"type":"PARAMETERIZED","attribute":"satisfaction-date-1","parameter":{"type":"PROCESS_VARIABLE","name":"Satisfaction Date"}},{"type":"PARAMETERIZED","attribute":"sla-count-breaches-1","parameter":{"type":"PROCESS_VARIABLE","name":"SLA Count Breaches"}},{"type":"PARAMETERIZED","attribute":"sla-count-completed-1","parameter":{"type":"PROCESS_VARIABLE","name":"SLA Count Completed"}},{"type":"PARAMETERIZED","attribute":"sla-count-ongoing-1","parameter":{"type":"PROCESS_VARIABLE","name":"SLA Count Ongoing"}},{"type":"PARAMETERIZED","attribute":"sla-count-paused-1","parameter":{"type":"PROCESS_VARIABLE","name":"SLA Count Paused"}},{"type":"PARAMETERIZED","attribute":"sla-definition-count-1","parameter":{"type":"PROCESS_VARIABLE","name":"SLA Definition Count"}},{"type":"PARAMETERIZED","attribute":"summary-36","parameter":{"type":"PROCESS_VARIABLE","name":"Summary"}},{"type":"PARAMETERIZED","attribute":"target-end-date-1","parameter":{"type":"PROCESS_VARIABLE","name":"Target End Date"}},{"type":"PARAMETERIZED","attribute":"target-start-date-1","parameter":{"type":"PROCESS_VARIABLE","name":"Target Start Date"}},{"type":"PARAMETERIZED","attribute":"url-1","parameter":{"type":"PROCESS_VARIABLE","name":"URL"}},{"type":"PARAMETERIZED","attribute":"work-category-1","parameter":{"type":"PROCESS_VARIABLE","name":"Work Category"}}]},"filters":[],"children":[]}]},{"name":"B","id":"b-1","visualization":{"type":"CHAPTER"},"filters":[],"children":[]}]},"metricsBar":[],"eventToShapeMappings":{"mappings":[]}}}