{
  "Unnamed: 0.1": 9034,
  "Unnamed: 0": 2940,
  "name": "Percentage of products without forecast",
  "query": "SELECT\nCOUNT(DISTINCT(\"Product ID\")) FILTER(\n\tWHERE (\n\t\tSELECT SUM(\"Statistical Fcst Qty\") = 0\n\t)\nAND \"Material Type ID\" = 'FERT'\n)\n/\nCOUNT(DISTINCT (\"Product ID\")) FILTER(\n\tWHERE \"Material Type ID\" = 'FERT'\n)\n* 100\nFROM \"defaultview-404\"",
  "description": "Percentage of products which could not be forecasted by the forecasting algorithm",
  "meta": "dashboard",
  "metric_vars": null,
  "view": "defaultview-404",
  "signalFragment": "SELECT\nCOUNT(DISTINCT(\"Product ID\")) FILTER(\n\tWHERE (\n\t\tSELECT SUM(\"Statistical Fcst Qty\") = 0\n\t)\nAND \"Material Type ID\" = 'FERT'\n)\n/\nCOUNT(DISTINCT (\"Product ID\")) FILTER(\n\tWHERE \"Material Type ID\" = 'FERT'\n)\n* 100\nFROM THIS_PROCESS",
  "process": "00_DEMO - SAP IBP S&OP (DO NOT CHANGE)",
  "origin": "../data/From_API/Solutions Demo Workspace/00_DEMO - SAP IBP S&OP (DO NOT CHANGE)/dashboards/Overview Dashboard_2024-02-01.json",
  "workspace_name": "Solutions Demo Workspace",
  "FragmentWordCount": 31,
  "descriptionWordCount": 12,
  "nameWordCount": 5,
  "FragmentLength": 233,
  "descriptionLength": 81,
  "nameLength": 39,
  "parser_column_names": "[]",
  "parser_values": "[\"100\", \"Product ID\", \"0\", \"Material Type ID\", \"FERT\", \"Statistical Fcst Qty\"]",
  "parser_error": null,
  "parser": "Signavio",
  "APIvalidated": "ok",
  "validationDataResponse": "[[10.0]]",
  "validationDataLength": 1,
  "view_columns": [
    "CaseId",
    "Activity",
    "End time",
    "ABC Id",
    "Actuals Qty",
    "Area",
    "Capacity Utilization",
    "Comment",
    "Consensus Demand",
    "Consensus Demand Delivered",
    "Consensus Demand Plan Qty",
    "Customer Receipts",
    "Event Created By User Id",
    "Forecast Open Output",
    "Freetext",
    "Independent Demand",
    "Independent Demand Supply",
    "Inventory Target",
    "Key Figure Name",
    "Marketing Forecast Qty",
    "Material Type ID",
    "MONTH",
    "MsgType",
    "New Value",
    "Old Value",
    "PLM Status",
    "Process Name",
    "Product Family",
    "Product ID",
    "Projected Stock",
    "Reason Code(s)",
    "Receipts",
    "Recommended Safety Stock",
    "Sales Forecast Qty",
    "Source of Change",
    "Statistical Fcst Qty",
    "Statistical Fcst Qty Bias (%)",
    "Statistical Fcst Qty Error (%)",
    "Status Modified Manually",
    "Step Status",
    "Stock on Hand",
    "XYZ Id"
  ],
  "filename": "1b403b3a3e",
  "json_filename_saved": "saved"
}